yamleaf/__init__.py
yamleaf/config_manager.py
yamleaf/exceptions.py
yamleaf/types.py
yamleaf/utils.py
yamleaf-0.1.0.dist-info/METADATA
yamleaf-0.1.0.dist-info/WHEEL
yamleaf-0.1.0.dist-info/RECORD
