Metadata-Version: 2.4
Name: yamleaf
Version: 0.1.0
Summary: A Python package for managing YAML configuration files while preserving structure, comments, and formatting with attribute and dictionary access
Project-URL: Homepage, https://github.com/mildthrone/yamleaf
Project-URL: Repository, https://github.com/mildthrone/yamleaf
Project-URL: Documentation, https://github.com/mildthrone/yamleaf
Project-URL: Bug Tracker, https://github.com/mildthrone/yamleaf/issues
Author-email: "Aaron Z." <mildthrone@proton.me>
License: MIT
Keywords: attributes,config,configuration,management,typing,yaml
Classifier: Development Status :: 4 - Beta
Classifier: Intended Audience :: Developers
Classifier: License :: OSI Approved :: MIT License
Classifier: Programming Language :: Python :: 3
Classifier: Programming Language :: Python :: 3.8
Classifier: Programming Language :: Python :: 3.9
Classifier: Programming Language :: Python :: 3.10
Classifier: Programming Language :: Python :: 3.11
Classifier: Programming Language :: Python :: 3.12
Classifier: Topic :: Software Development :: Libraries :: Python Modules
Classifier: Topic :: System :: Systems Administration
Classifier: Topic :: Text Processing :: Markup
Requires-Python: >=3.8
Requires-Dist: ruamel-yaml>=0.17.0
Provides-Extra: dev
Requires-Dist: black>=22.0; extra == 'dev'
Requires-Dist: flake8>=5.0; extra == 'dev'
Requires-Dist: isort>=5.0; extra == 'dev'
Requires-Dist: mypy>=1.0; extra == 'dev'
Requires-Dist: pre-commit>=2.20.0; extra == 'dev'
Requires-Dist: pytest-cov>=4.0; extra == 'dev'
Requires-Dist: pytest>=7.0; extra == 'dev'
Provides-Extra: test
Requires-Dist: pytest-cov>=4.0; extra == 'test'
Requires-Dist: pytest-mock>=3.10.0; extra == 'test'
Requires-Dist: pytest>=7.0; extra == 'test'
